{
"skeleton": {
	"hash": "Ky4Z0C3D3g07A+wO/AtloWEFtsU",
	"spine": "3.8.96",
	"x": -196.87,
	"y": -81.04,
	"width": 332.78,
	"height": 1038.09,
	"images": "./Parts/",
	"audio": ""
},
"bones": [
	{ "name": "root" },
	{ "name": "control", "parent": "root", "length": 527.95, "rotation": 88.3, "x": -24.88, "y": -15.26 },
	{ "name": "control_1", "parent": "control", "length": 434.28, "rotation": -0.71, "x": 525.3, "y": 1.23 },
	{ "name": "target2", "parent": "root", "x": 6.39, "y": 950.62, "color": "ff3f00ff" },
	{ "name": "control_2", "parent": "root", "length": 50.78, "rotation": 90.76, "x": 234.57, "y": 1.9 },
	{ "name": "control_3", "parent": "control_2", "length": 46.04, "rotation": -1.61, "x": -48, "y": 0.25 },
	{ "name": "control_4", "parent": "control_2", "length": 47.39, "rotation": 0.38, "x": -95.94, "y": 0.59 },
	{ "name": "control_5", "parent": "control_2", "length": 56.21, "rotation": 0.91, "x": -143.9, "y": 1.21 },
	{ "name": "control_6", "parent": "control_2", "length": 46.73, "rotation": -0.79, "x": -191.71, "y": 2.22 },
	{ "name": "control_7", "parent": "control_2", "length": 48.75, "rotation": -2.96, "x": -239.78, "y": 2.09 },
	{ "name": "control_8", "parent": "control_2", "length": 35.23, "rotation": 3.53, "x": -287.84, "y": 1.57 },
	{ "name": "control_9", "parent": "control_2", "length": 41.98, "rotation": -2.51, "x": -335.75, "y": 1.25 },
	{ "name": "control_10", "parent": "control_2", "length": 45.38, "rotation": 2.6, "x": -383.7, "y": 1.65 },
	{ "name": "control_11", "parent": "control_2", "length": 40.67, "rotation": -5.29, "x": -431.7, "y": 2.23 },
	{ "name": "control_12", "parent": "control_2", "length": 40.64, "rotation": 4.19, "x": -479.71, "y": 2.47 },
	{ "name": "control_13", "parent": "control_2", "length": 48.82, "rotation": 1.4, "x": -527.5, "y": 1.83 },
	{ "name": "control_14", "parent": "control_2", "length": 52.82, "rotation": -3.56, "x": -575.58, "y": 1.38 },
	{ "name": "control_15", "parent": "control_2", "length": 44.01, "rotation": 0.74, "x": -623.61, "y": 1.36 },
	{ "name": "control_16", "parent": "control_2", "length": 48.86, "rotation": 4.84, "x": -671.67, "y": 1.25 },
	{ "name": "control_17", "parent": "control_2", "length": 47.39, "rotation": -4.39, "x": -719.55, "y": 0.42 },
	{ "name": "control_18", "parent": "control_2", "length": 42.66, "rotation": 3.56, "x": -767.42, "y": -0.41 },
	{ "name": "control_19", "parent": "control_2", "length": 40.63, "rotation": -1.5, "x": -815.46, "y": -0.45 },
	{ "name": "control_20", "parent": "control_2", "length": 40.03, "rotation": 4.68, "x": -863.49, "y": -0.33 },
	{ "name": "control_21", "parent": "control_2", "length": 57.5, "rotation": -3.27, "x": -911.4, "y": -0.64 }
],
"slots": [
	{ "name": "path", "bone": "root", "attachment": "path" },
	{ "name": "tentacle", "bone": "root", "attachment": "tentacle" }
],
"ik": [
	{
		"name": "target",
		"bones": [ "control", "control_1" ],
		"target": "target2",
		"bendPositive": false
	}
],
"path": [
	{
		"name": "path",
		"order": 1,
		"bones": [ "control_21", "control_20", "control_19", "control_18", "control_17", "control_16", "control_15", "control_14", "control_13", "control_12", "control_11", "control_10", "control_9", "control_8", "control_7", "control_6", "control_5", "control_4", "control_3", "control_2" ],
		"target": "path",
		"spacingMode": "percent",
		"rotateMode": "chainScale",
		"spacing": 0.05
	}
],
"skins": [
	{
		"name": "default",
		"attachments": {
			"path": {
				"path": {
					"type": "path",
					"lengths": [ 204.26, 498.03, 738.97, 957.18, 1133.06, 1250.6, 2214.36 ],
					"vertexCount": 21,
					"vertices": [ 1, 0, -23.38, -75.73, 1, 1, 0, -22.98, -21.77, 1, 1, 1, 52.88, -0.52, 1, 1, 1, 54.9, 99.08, 1, 1, 1, 165.8, 94.46, 1, 1, 1, 287.12, 89.41, 1, 1, 1, 295.24, -82.35, 1, 1, 1, 392.13, -77.48, 1, 1, 1, 508.41, -71.62, 1, 1, 1, 420.77, 71.71, 1, 1, 2, 31.04, 70.63, 1, 1, 2, 154.63, 70.55, 1, 1, 2, 86.79, -47.45, 1, 1, 2, 198.86, -45.55, 1, 1, 2, 310.74, -43.65, 1, 1, 2, 272.01, 50.06, 1, 1, 2, 332.86, 52.17, 1, 1, 2, 385.23, 53.99, 1, 1, 2, 366.48, -6.87, 1, 1, 2, 431.99, 0.43, 1, 1, 1, 992.21, 6.64, 1 ]
				}
			},
			"tentacle": {
				"tentacle": {
					"type": "mesh",
					"uvs": [ 0.41862, 0.16292, 0.42043, 0.14752, 0.42341, 0.13331, 0.42639, 0.11904, 0.42963, 0.10356, 0.43256, 0.08956, 0.43508, 0.07752, 0.43843, 0.06147, 0.44149, 0.04688, 0.44356, 0.03695, 0.44656, 0.02261, 0.47108, 0.02355, 0.47524, 0.03636, 0.47841, 0.04611, 0.48342, 0.06155, 0.48894, 0.07855, 0.49307, 0.09127, 0.49397, 0.10559, 0.49498, 0.12182, 0.49679, 0.13553, 0.49858, 0.14906, 0.50025, 0.16807, 0.50159, 0.18324, 0.50383, 0.21823, 0.50366, 0.23592, 0.50345, 0.25656, 0.50495, 0.2773, 0.50655, 0.29947, 0.50476, 0.31918, 0.50292, 0.33947, 0.50722, 0.36496, 0.51009, 0.38197, 0.51109, 0.40145, 0.51212, 0.42166, 0.5134, 0.44003, 0.51513, 0.46492, 0.51725, 0.48806, 0.51934, 0.51089, 0.52125, 0.53532, 0.52322, 0.56039, 0.52282, 0.58616, 0.52239, 0.6136, 0.52388, 0.63611, 0.52556, 0.66162, 0.52818, 0.69223, 0.53094, 0.72442, 0.53401, 0.753, 0.537, 0.78082, 0.53889, 0.80835, 0.54163, 0.84834, 0.54917, 0.87897, 0.55826, 0.91587, 0.56122, 0.95534, 0.56457, 1, 0.34779, 1, 0.35113, 0.9603, 0.35462, 0.91867, 0.35747, 0.88484, 0.36087, 0.8444, 0.36335, 0.81484, 0.36609, 0.78221, 0.36873, 0.75083, 0.37135, 0.71967, 0.37385, 0.68987, 0.37603, 0.66399, 0.37861, 0.63329, 0.38064, 0.60914, 0.38323, 0.57825, 0.38504, 0.55679, 0.3871, 0.53222, 0.38886, 0.51124, 0.39118, 0.48364, 0.39283, 0.46403, 0.39539, 0.43357, 0.39637, 0.42192, 0.39838, 0.39796, 0.39978, 0.38137, 0.40139, 0.36223, 0.4034, 0.33833, 0.40525, 0.31631, 0.40701, 0.29532, 0.4086, 0.27645, 0.4105, 0.25374, 0.41198, 0.23623, 0.4138, 0.21451, 0.41523, 0.19756, 0.41693, 0.17725 ],
					"triangles": [ 54, 55, 53, 55, 52, 53, 52, 55, 56, 52, 56, 51, 56, 50, 51, 56, 57, 50, 57, 58, 49, 57, 49, 50, 58, 59, 49, 59, 48, 49, 48, 59, 60, 60, 46, 47, 48, 60, 47, 60, 61, 46, 46, 61, 45, 61, 62, 45, 45, 62, 44, 63, 64, 43, 44, 63, 43, 62, 63, 44, 43, 64, 65, 43, 65, 42, 42, 65, 41, 65, 66, 41, 67, 68, 40, 40, 68, 39, 41, 67, 40, 66, 67, 41, 38, 69, 37, 68, 69, 38, 39, 68, 38, 69, 70, 37, 71, 72, 35, 36, 71, 35, 70, 71, 36, 70, 36, 37, 72, 73, 34, 35, 72, 34, 34, 73, 33, 73, 74, 33, 32, 75, 31, 33, 75, 32, 33, 74, 75, 75, 76, 31, 29, 79, 28, 31, 76, 30, 76, 77, 30, 78, 79, 29, 77, 78, 29, 30, 77, 29, 79, 80, 28, 28, 80, 27, 27, 80, 26, 80, 81, 26, 26, 81, 25, 81, 82, 25, 25, 83, 24, 82, 83, 25, 83, 84, 24, 85, 86, 22, 23, 85, 22, 84, 85, 23, 24, 84, 23, 86, 0, 21, 1, 2, 20, 0, 1, 20, 2, 19, 20, 21, 0, 20, 22, 86, 21, 5, 6, 15, 16, 5, 15, 2, 3, 19, 3, 18, 19, 5, 16, 17, 4, 5, 17, 4, 17, 18, 3, 4, 18, 9, 10, 11, 9, 11, 12, 8, 9, 12, 8, 12, 13, 7, 8, 13, 14, 7, 13, 6, 7, 14, 15, 6, 14 ],
					"vertices": [ 3, 5, -34.06, 39.39, 0.03, 6, 13.88, 39.44, 0.7635, 7, 61.43, 39.86, 0.2065, 3, 5, -18.6, 38.07, 0.1625, 6, 29.33, 38.12, 0.8015, 7, 76.9, 38.7, 0.036, 2, 5, -4.31, 35.55, 0.4125, 6, 43.63, 35.6, 0.5875, 3, 4, -37.68, 33.19, 0.017, 5, 10.05, 33.02, 0.6705, 6, 57.99, 33.07, 0.3125, 3, 4, -22.14, 30.32, 0.103, 5, 25.62, 30.27, 0.7845, 6, 73.56, 30.33, 0.1125, 3, 4, -8.06, 27.72, 0.3045, 5, 39.71, 27.79, 0.6755, 6, 87.65, 27.85, 0.02, 2, 4, 4.03, 25.49, 0.5905, 5, 51.82, 25.66, 0.4095, 2, 4, 20.15, 22.52, 0.8445, 5, 67.97, 22.81, 0.1555, 2, 4, 34.81, 19.81, 0.9725, 5, 82.65, 20.22, 0.0275, 1, 4, 44.79, 17.97, 1, 1, 4, 59.2, 15.31, 1, 1, 4, 58.86, -9.22, 1, 1, 4, 46.15, -13.69, 1, 2, 4, 36.48, -17.08, 0.9725, 5, 84.61, -16.66, 0.0275, 2, 4, 21.16, -22.46, 0.8445, 5, 69.33, -22.16, 0.1555, 2, 4, 4.29, -28.38, 0.5905, 5, 52.52, -28.21, 0.4095, 3, 4, -8.33, -32.81, 0.3045, 5, 39.93, -32.74, 0.6755, 6, 87.88, -32.68, 0.02, 3, 4, -22.63, -34.05, 0.103, 5, 25.65, -34.1, 0.7845, 6, 73.59, -34.04, 0.1125, 3, 4, -38.83, -35.45, 0.017, 5, 9.45, -35.63, 0.6705, 6, 57.4, -35.57, 0.3125, 2, 5, -4.19, -37.87, 0.4125, 6, 43.76, -37.82, 0.5875, 3, 5, -17.65, -40.09, 0.1625, 6, 30.29, -40.04, 0.8015, 7, 78.68, -39.44, 0.036, 3, 5, -36.6, -42.36, 0.03, 6, 11.35, -42.32, 0.7635, 7, 59.76, -41.92, 0.2065, 3, 6, -3.77, -44.14, 0.4715, 7, 44.65, -43.89, 0.4865, 8, 92.04, -44.93, 0.042, 3, 6, -38.67, -47.5, 0.142, 7, 9.79, -47.62, 0.6275, 8, 57.14, -48.31, 0.2305, 4, 6, -56.36, -47.88, 0.0265, 7, -7.89, -48.19, 0.409, 8, 39.45, -48.7, 0.5345, 9, 86.63, -49.74, 0.03, 3, 7, -28.52, -48.86, 0.1445, 8, 18.81, -49.17, 0.673, 9, 65.98, -49.83, 0.1825, 4, 7, -49.18, -51.24, 0.0205, 8, -1.86, -51.34, 0.487, 9, 45.27, -51.62, 0.4655, 10, 93.27, -51.67, 0.027, 3, 8, -23.97, -53.67, 0.1925, 9, 23.12, -53.55, 0.637, 10, 71.11, -53.57, 0.1705, 3, 8, -43.73, -52.52, 0.0325, 9, 3.39, -52.04, 0.493, 10, 51.39, -52.03, 0.4745, 3, 9, -16.93, -50.49, 0.2045, 10, 31.07, -50.46, 0.7575, 11, 79.55, -49.76, 0.038, 3, 9, -42.34, -55.16, 0.0355, 10, 5.64, -55.09, 0.75, 11, 54.18, -54.68, 0.2145, 3, 10, -11.33, -58.18, 0.4595, 11, 37.24, -57.97, 0.5095, 12, 85.88, -57.32, 0.031, 3, 10, -30.8, -59.43, 0.1605, 11, 17.79, -59.43, 0.653, 12, 66.45, -59.02, 0.1865, 4, 10, -50.99, -60.72, 0.0245, 11, -2.39, -60.96, 0.477, 12, 46.29, -60.78, 0.4675, 13, 94.15, -60.98, 0.031, 3, 11, -20.72, -62.68, 0.1885, 12, 27.98, -62.72, 0.625, 13, 75.83, -62.88, 0.1865, 4, 11, -45.56, -65.02, 0.0315, 12, 3.17, -65.35, 0.47, 13, 51.02, -65.45, 0.468, 14, 98.21, -66.43, 0.0305, 3, 12, -19.88, -68.31, 0.1885, 13, 27.96, -68.36, 0.627, 14, 75.12, -69.04, 0.1845, 4, 12, -42.62, -71.23, 0.0315, 13, 5.22, -71.22, 0.473, 14, 52.34, -71.63, 0.4655, 15, 98.93, -72.75, 0.03, 3, 13, -19.13, -73.96, 0.1905, 14, 27.96, -74.06, 0.627, 15, 74.51, -74.78, 0.1825, 4, 13, -44.13, -76.77, 0.032, 14, 2.93, -76.56, 0.4755, 15, 49.44, -76.87, 0.4595, 16, 98.78, -75.73, 0.033, 3, 14, -22.84, -76.72, 0.1925, 15, 23.67, -76.59, 0.613, 16, 73, -75.88, 0.1945, 4, 14, -50.29, -76.88, 0.0325, 15, -3.77, -76.3, 0.457, 16, 45.56, -76.03, 0.4805, 17, 93.81, -75.87, 0.03, 3, 15, -26.27, -77.89, 0.1805, 16, 23.09, -77.99, 0.637, 17, 71.34, -77.89, 0.1825, 4, 15, -51.77, -79.7, 0.0295, 16, -2.38, -80.21, 0.478, 17, 45.88, -80.19, 0.43, 18, 93.35, -80.74, 0.0625, 4, 16, -32.92, -83.48, 0.1925, 17, 15.34, -83.54, 0.495, 18, 62.79, -83.87, 0.283, 19, 108.56, -86.13, 0.0295, 4, 16, -65.05, -86.91, 0.0325, 17, -16.77, -87.07, 0.28, 18, 30.65, -87.17, 0.507, 19, 76.34, -88.62, 0.1805, 4, 17, -45.27, -90.83, 0.0625, 18, 2.12, -90.72, 0.448, 19, 47.73, -91.45, 0.427, 20, 97.96, -89.66, 0.0625, 4, 18, -25.64, -94.17, 0.1945, 19, 19.89, -94.21, 0.493, 20, 70.19, -93.13, 0.2825, 21, 119.07, -92.33, 0.03, 4, 18, -53.14, -96.52, 0.033, 19, -7.65, -95.87, 0.2795, 20, 42.7, -95.5, 0.505, 21, 91.6, -94.95, 0.1825, 4, 19, -47.66, -98.29, 0.0625, 20, 2.77, -98.95, 0.445, 21, 51.7, -98.75, 0.43, 22, 99.48, -98.99, 0.0625, 4, 20, -27.73, -107.02, 0.1925, 21, 21.28, -107.1, 0.495, 22, 69.03, -107.26, 0.282, 23, 115.17, -108.85, 0.0305, 4, 20, -64.46, -116.75, 0.0325, 21, -15.37, -117.16, 0.28, 22, 32.36, -117.22, 0.503, 23, 78.34, -118.21, 0.1845, 3, 21, -54.74, -121.16, 0.0625, 22, -7.02, -121.13, 0.45267, 23, 38.9, -121.47, 0.48483, 2, 22, -51.59, -125.56, 0.28244, 23, -5.74, -125.16, 0.71756, 2, 22, -56.79, 91.17, 0.28244, 23, -7.36, 91.62, 0.71756, 3, 21, -65.27, 88.73, 0.0625, 22, -17.03, 88.78, 0.45267, 23, 32.36, 88.58, 0.48483, 4, 20, -70.82, 86.81, 0.0325, 21, -23.56, 86.33, 0.28, 22, 24.68, 86.28, 0.503, 23, 74.02, 85.4, 0.1845, 4, 20, -36.95, 84.55, 0.1925, 21, 10.33, 84.38, 0.495, 22, 58.57, 84.25, 0.282, 23, 107.86, 82.81, 0.0305, 4, 19, -42.23, 82.44, 0.0625, 20, 3.55, 81.86, 0.445, 21, 50.85, 82.06, 0.43, 22, 99.07, 81.83, 0.0625, 4, 18, -62.56, 78.88, 0.033, 19, -12.69, 79.71, 0.2795, 20, 33.15, 79.89, 0.505, 21, 80.47, 80.36, 0.1825, 4, 18, -29.89, 76.69, 0.1945, 19, 19.92, 76.7, 0.493, 20, 65.82, 77.72, 0.2825, 21, 113.16, 78.48, 0.03, 4, 17, -47.07, 74.45, 0.0625, 18, 1.53, 74.57, 0.448, 19, 51.28, 73.8, 0.427, 20, 97.24, 75.63, 0.0625, 4, 16, -63.67, 72.74, 0.0325, 17, -15.86, 72.58, 0.28, 18, 32.73, 72.48, 0.507, 19, 82.42, 70.93, 0.1805, 4, 16, -33.82, 70.87, 0.1925, 17, 13.99, 70.8, 0.495, 18, 62.57, 70.47, 0.283, 19, 112.19, 68.18, 0.0295, 4, 15, -54.86, 69.82, 0.0295, 16, -7.9, 69.24, 0.478, 17, 39.91, 69.25, 0.43, 18, 88.48, 68.73, 0.0625, 3, 15, -24.14, 67.39, 0.1805, 16, 22.85, 67.31, 0.637, 17, 70.67, 67.41, 0.1825, 4, 14, -48.87, 64.94, 0.0325, 15, 0.01, 65.48, 0.457, 16, 47.03, 65.79, 0.4805, 17, 94.86, 65.96, 0.03, 3, 14, -17.93, 63.01, 0.1925, 15, 30.91, 63.03, 0.613, 16, 77.97, 63.84, 0.1945, 4, 13, -45.21, 61.45, 0.032, 14, 3.57, 61.66, 0.4755, 15, 52.38, 61.33, 0.4595, 16, 99.46, 62.49, 0.033, 3, 13, -20.58, 60.22, 0.1905, 14, 28.17, 60.13, 0.627, 15, 76.96, 59.38, 0.1825, 4, 12, -47.7, 59.15, 0.0315, 13, 0.44, 59.17, 0.473, 14, 49.18, 58.81, 0.4655, 15, 97.95, 57.72, 0.03, 3, 12, -20.03, 57.83, 0.1885, 13, 28.11, 57.78, 0.627, 14, 76.83, 57.09, 0.1845, 4, 11, -47.65, 57.27, 0.0315, 12, -0.38, 56.9, 0.47, 13, 47.75, 56.8, 0.468, 14, 96.46, 55.86, 0.0305, 3, 11, -17.14, 55.45, 0.1885, 12, 30.16, 55.44, 0.625, 13, 78.29, 55.28, 0.1865, 4, 10, -52.76, 55.01, 0.0245, 11, -5.46, 54.75, 0.477, 12, 41.84, 54.88, 0.4675, 13, 89.97, 54.69, 0.031, 3, 10, -28.78, 53.31, 0.1605, 11, 18.53, 53.32, 0.653, 12, 65.85, 53.74, 0.1865, 3, 10, -12.17, 52.13, 0.4595, 11, 35.15, 52.33, 0.5095, 12, 82.48, 52.95, 0.031, 3, 9, -41.15, 50.71, 0.0355, 10, 6.98, 50.77, 0.75, 11, 54.33, 51.19, 0.2145, 3, 9, -17.22, 49.04, 0.2045, 10, 30.91, 49.08, 0.7575, 11, 78.27, 49.76, 0.038, 3, 8, -44.11, 47.04, 0.0325, 9, 4.82, 47.51, 0.493, 10, 52.94, 47.51, 0.4745, 3, 8, -23.06, 45.96, 0.1925, 9, 25.84, 46.05, 0.637, 10, 73.96, 46.02, 0.1705, 4, 7, -52.43, 45.06, 0.0205, 8, -4.16, 44.99, 0.487, 9, 44.72, 44.73, 0.4655, 10, 92.84, 44.68, 0.027, 3, 7, -29.65, 44.12, 0.1445, 8, 18.61, 43.82, 0.673, 9, 67.46, 43.15, 0.1825, 3, 7, -12.1, 43.39, 0.4355, 8, 36.15, 42.92, 0.5345, 9, 84.99, 41.93, 0.03, 3, 6, -37.84, 42.61, 0.06183, 7, 9.68, 42.49, 0.70767, 8, 57.92, 41.8, 0.2305, 3, 6, -20.85, 41.73, 0.20111, 7, 26.68, 41.79, 0.74289, 8, 74.91, 40.93, 0.056, 2, 6, -0.49, 40.67, 0.48033, 7, 47.04, 40.94, 0.51967 ],
					"hull": 87,
					"edges": [ 44, 46, 102, 104, 104, 106, 108, 110, 110, 112, 98, 100, 100, 102, 112, 114, 114, 116, 94, 96, 96, 98, 116, 118, 118, 120, 20, 22, 106, 108, 104, 110, 112, 102, 100, 114, 98, 116, 96, 118, 94, 120, 90, 92, 92, 94, 120, 122, 122, 124, 92, 122, 90, 124, 86, 88, 88, 90, 124, 126, 126, 128, 88, 126, 86, 128, 82, 84, 84, 86, 128, 130, 130, 132, 84, 130, 82, 132, 78, 80, 80, 82, 132, 134, 134, 136, 80, 134, 136, 78, 74, 76, 76, 78, 136, 138, 138, 140, 76, 138, 140, 74, 70, 72, 72, 74, 140, 142, 142, 144, 72, 142, 144, 70, 66, 68, 68, 70, 144, 146, 146, 148, 68, 146, 148, 66, 62, 64, 64, 66, 148, 150, 150, 152, 64, 150, 152, 62, 58, 60, 60, 62, 152, 154, 154, 156, 60, 154, 156, 58, 54, 56, 56, 58, 156, 158, 158, 160, 56, 158, 54, 160, 160, 162, 162, 164, 50, 52, 52, 54, 162, 52, 50, 164, 46, 48, 48, 50, 164, 166, 166, 168, 48, 166, 46, 168, 44, 172, 168, 170, 170, 172, 40, 42, 42, 44, 2, 0, 0, 172, 0, 42, 40, 2, 2, 4, 4, 6, 36, 38, 38, 40, 4, 38, 36, 6, 32, 34, 34, 36, 6, 8, 8, 10, 34, 8, 10, 32, 28, 30, 30, 32, 10, 12, 12, 14, 30, 12, 14, 28, 14, 16, 26, 28, 16, 26, 22, 24, 24, 26, 16, 18, 18, 20, 24, 18 ],
					"width": 1000,
					"height": 1000
				}
			}
		}
	}
],
"animations": {
	"moving": {
		"path": {
			"path": {
				"position": [
					{ "position": -0.2, "curve": 0.25, "c3": 0.75 },
					{ "time": 1.6667, "curve": 0.25, "c3": 0.75 },
					{ "time": 3.3333, "position": -0.2 }
				]
			}
		}
	}
}
}